patee/__init__.py
patee/core_types.py
patee/input_types.py
patee/patee.py
patee/step_types.py
patee/steps_executor.py
patee/steps/__init__.py
patee/steps/csv_extractor_step.py
patee/steps/docling_extractor_step.py
patee/steps/human_in_the_loop_processor_step.py
patee/steps/noop_processor_step.py
patee/steps/regex_filter_processor_step.py
patee/steps/regex_replace_processor_step.py
patee/steps/text_extractor_step.py
patee/steps/text_writer_processor_step.py
patee/steps_builder/__init__.py
patee/steps_builder/default_steps_builder.py
patee-0.4.0.dist-info/licenses/LICENSE
patee-0.4.0.dist-info/METADATA
patee-0.4.0.dist-info/WHEEL
patee-0.4.0.dist-info/top_level.txt
patee-0.4.0.dist-info/zip-safe
patee-0.4.0.dist-info/RECORD
