Metadata-Version: 2.4
Name: patee
Version: 0.4.0
Summary: Parallel text extraction and processing customizable pipeline
Home-page: https://github.com/hbiarge/patee
Author: Hugo Biarge
Author-email: hugo@arosbi.com
License: MIT
Project-URL: Release notes, https://github.com/hbiarge/patee/releases
Project-URL: Source, https://github.com/hbiarge/patee
Classifier: Development Status :: 4 - Beta
Classifier: Environment :: Console
Classifier: Intended Audience :: Developers
Classifier: Intended Audience :: Science/Research
Classifier: License :: OSI Approved :: MIT License
Classifier: Operating System :: POSIX :: Linux
Classifier: Operating System :: MacOS :: MacOS X
Classifier: Operating System :: Microsoft :: Windows
Classifier: Programming Language :: Python :: 3
Classifier: Programming Language :: Python :: 3.10
Classifier: Programming Language :: Python :: 3.11
Classifier: Programming Language :: Python :: 3.12
Classifier: Topic :: Scientific/Engineering
Requires-Python: >=3.10
License-File: LICENSE
Requires-Dist: docling~=2.28.0
Requires-Dist: PyYAML~=6.0.2
Dynamic: license-file
